paralelo_serial/Probador.v
// Módulo probador: generador de señales y monitor de datos
module Probador(
	output reg		clk_4f,
	output reg		clk_32f,
	output reg		[7:0] data_in,
	output reg		valid_in,
	output reg 		reset_L,
	input wire data_out
	);

	// Bloque de procedimiento, no sintetizable, se recorre una única vez
	// Generalmente, los initial sólo se usan en los testbench o probadores
	// Se recomienda siempre sincronizar con el reloj y utilizar
	// asignaciones no bloqueantes en la generación de señales

	initial begin
		$dumpfile("P1_paralelo_serial.vcd"); // Nombre de archivo del "dump"
		$dumpvars; // Directiva para "dumpear" variables

			data_in = 'hFF;
			reset_L <= 0;
			valid_in <= 0;

			@(posedge clk_4f);
					reset_L <= 0;
					valid_in <= 0;

			@(posedge clk_4f);
					reset_L <= 1;
					data_in <= 'hFF;
					valid_in <= 1;

			@(posedge clk_4f);
        	data_in <= 'hFF;
        	valid_in <= 1;

      @(posedge clk_4f);
        	data_in <= 'hEE;
        	valid_in <= 1;

			@(posedge clk_4f);
						data_in <= 'hEE;
						valid_in <= 1;

			@(posedge clk_4f);
						data_in <= 'hEE;
						valid_in <= 1;

		$finish;

	end

	// Reloj
	initial	clk_4f	<= 1;
	always  #8		clk_4f 	<= ~clk_4f;

	// Reloj
	initial	clk_32f	<= 1;
	always  #1 	clk_32f <= ~clk_32f;

endmodule

paralelo_serial/paralelo_serial.v
module paralelo_serial(
	input		clk_4f,
	input		clk_32f,
	input 	reset_L,
	input		[7:0] data_in,
	input		valid_in,
	output reg	data_out
	);
	reg [2:0] selector = 'b000;
	reg [7:0] tmp_out;

always @ (posedge clk_32f or posedge reset_L) begin
		tmp_out <= data_in;
		if (reset_L == 0) begin
			data_out <= 0;
		end
		else	begin
			if (valid_in == 0) begin
				tmp_out <= 'hBC;
			end
			else begin
					if (selector == 'b000) begin
						data_out <= tmp_out[7];
					end
					if (selector == 'b001) begin
						data_out <= tmp_out[6];
					end
					if (selector == 'b010) begin
						data_out <= tmp_out[5];
					end
					if (selector == 'b011) begin
						data_out <= tmp_out[4];
					end
					if (selector == 'b100) begin
						data_out <= tmp_out[3];
					end
					if (selector == 'b101) begin
						data_out <= tmp_out[2];
					end
					if (selector == 'b110) begin
						data_out <= tmp_out[1];
					end
					if (selector == 'b111) begin
						data_out <= tmp_out[0];
					end
			end
			if (selector == 7 ) begin
				selector <= 'b000;
			end
			else begin
				selector <= selector + 'b001;
			end
		end
end

endmodule

paralelo_serial/Banco_pruebas.v
`timescale 	1s				/ 100ps
// escala	unidad temporal (valor de "#1") / precisión
// includes de archivos de verilog
// Pueden omitirse y llamarse desde el testbench
`include "paralelo_serial.v"
`include "Probador.v"


module Banco_pruebas; // Testbench
	// Por lo general, las señales en el banco de pruebas son wires.
	// No almacenan un valor, son manejadas por otras instancias de módulos.
	wire		clk_4f, clk_32f, valid_in, reset_L;
	wire		[7:0] data_in;
	wire		data_out;

	// Descripción conductual
paralelo_serial paralelo_serial_conductual( /*AUTOINST*/
				  // Outputs
				  .data_out		(data_out),
				  // Inputs
				  .clk_4f		(clk_4f),
				  .clk_32f		(clk_32f),
				  .data_in		(data_in[7:0]),
				  .valid_in		(valid_in),
				  .reset_L		(reset_L));


	// Probador: generador de señales y monitor
Probador probador( /*AUTOINST*/
			  // Outputs
			  .clk_4f		(clk_4f),
			  .clk_32f		(clk_32f),
			  .data_in		(data_in[7:0]),
			  .valid_in		(valid_in),
			  .reset_L		(reset_L),
			  // Inputs
			  .data_out		(data_out));

endmodule

paralelo_serial/P1_paralelo_serial.vcd
$date
	Thu Oct 21 22:38:58 2021
$end
$version
	Icarus Verilog
$end
$timescale
	100ps
$end
$scope module Banco_pruebas $end
$var wire 1 ! valid_in $end
$var wire 1 " reset_L $end
$var wire 1 # data_out $end
$var wire 8 $ data_in [7:0] $end
$var wire 1 % clk_4f $end
$var wire 1 & clk_32f $end
$scope module paralelo_serial_conductual $end
$var wire 1 ! valid_in $end
$var wire 1 " reset_L $end
$var wire 8 ' data_in [7:0] $end
$var wire 1 % clk_4f $end
$var wire 1 & clk_32f $end
$var reg 1 # data_out $end
$var reg 3 ( selector [2:0] $end
$var reg 8 ) tmp_out [7:0] $end
$upscope $end
$scope module probador $end
$var wire 1 # data_out $end
$var reg 1 & clk_32f $end
$var reg 1 % clk_4f $end
$var reg 8 * data_in [7:0] $end
$var reg 1 " reset_L $end
$var reg 1 ! valid_in $end
$upscope $end
$upscope $end
$enddefinitions $end
#0
$dumpvars
b11111111 *
b11111111 )
b0 (
b11111111 '
1&
1%
b11111111 $
0#
0"
0!
$end
#10000000000
0&
#20000000000
1&
#30000000000
0&
#40000000000
1&
#50000000000
0&
#60000000000
1&
#70000000000
0&
#80000000000
1&
0%
#90000000000
0&
#100000000000
1&
#110000000000
0&
#120000000000
1&
#130000000000
0&
#140000000000
1&
#150000000000
0&
#160000000000
b1 (
1#
1!
1"
1&
1%
#170000000000
0&
#180000000000
b10 (
1&
#190000000000
0&
#200000000000
b11 (
1&
#210000000000
0&
#220000000000
b100 (
1&
#230000000000
0&
#240000000000
b101 (
1&
0%
#250000000000
0&
#260000000000
b110 (
1&
#270000000000
0&
#280000000000
b111 (
1&
#290000000000
0&
#300000000000
b0 (
1&
#310000000000
0&
#320000000000
b1 (
1&
1%
#330000000000
0&
#340000000000
b10 (
1&
#350000000000
0&
#360000000000
b11 (
1&
#370000000000
0&
#380000000000
b100 (
1&
#390000000000
0&
#400000000000
b101 (
1&
0%
#410000000000
0&
#420000000000
b110 (
1&
#430000000000
0&
#440000000000
b111 (
1&
#450000000000
0&
#460000000000
b0 (
1&
#470000000000
0&
#480000000000
b1 (
b11101110 $
b11101110 '
b11101110 *
1&
1%
#490000000000
0&
#500000000000
b10 (
b11101110 )
1&
#510000000000
0&
#520000000000
b11 (
1&
#530000000000
0&
#540000000000
b100 (
0#
1&
#550000000000
0&
#560000000000
b101 (
1#
1&
0%
#570000000000
0&
#580000000000
b110 (
1&
#590000000000
0&
#600000000000
b111 (
1&
#610000000000
0&
#620000000000
b0 (
0#
1&
#630000000000
0&
#640000000000
b1 (
1#
1&
1%
#650000000000
0&
#660000000000
b10 (
1&
#670000000000
0&
#680000000000
b11 (
1&
#690000000000
0&
#700000000000
b100 (
0#
1&
#710000000000
0&
#720000000000
b101 (
1#
1&
0%
#730000000000
0&
#740000000000
b110 (
1&
#750000000000
0&
#760000000000
b111 (
1&
#770000000000
0&
#780000000000
b0 (
0#
1&
#790000000000
0&
#800000000000
b1 (
1#
1&
1%
